{
  "nodes": [
    {
      "id": "e6c9a98b-ab04-4c8a-84d5-23ed0b6ffc7f",
      "type": "二级标题",
      "properties": {
        "实体名": "盒片叠的装载"
      }
    },
    {
      "id": "3eb5f2ab-e036-4b7d-91cb-d4fff4a0143b",
      "type": "二级标题",
      "properties": {
        "实体名": "叠的装载"
      }
    },
    {
      "id": "59b97a49-344f-47d4-8284-680066c6045b",
      "type": "设备",
      "properties": {
        "实体名": "电机2M974",
        "设备类型": "电机",
        "位置": "盒片叠传送带",
        "操作方式": "驱动",
        "操作细节": "将盒片叠放置到椅子上",
        "缩写": null
      }
    },
    {
      "id": "6d943eb5-2048-49e7-9431-71b714735565",
      "type": "设备",
      "properties": {
        "实体名": "传感器2S5864",
        "设备类型": "传感器",
        "位置": "椅子上",
        "操作方式": "检测",
        "操作细节": "盒片叠的存在",
        "缩写": null
      }
    },
    {
      "id": "1f979cc4-6b10-4f92-bdfe-9c4e298b4513",
      "type": "二级标题",
      "properties": {
        "实体名": "盒片叠置零"
      }
    },
    {
      "id": "e117c378-1f8c-42fc-aafb-fe9ef290cfb8",
      "type": "设备",
      "properties": {
        "实体名": "电机2M3231",
        "设备类型": "电机",
        "位置": "盒片叠椅子",
        "操作方式": "倾斜",
        "操作细节": "控制椅子支撑支臂的运动",
        "缩写": null
      }
    },
    {
      "id": "0f333d81-ccbf-4a1b-8296-03b6468700f9",
      "type": "设备",
      "properties": {
        "实体名": "电机2M3232",
        "设备类型": "电机",
        "位置": "盒片叠椅子",
        "操作方式": "转动",
        "操作细节": "控制组件转动",
        "缩写": null
      }
    },
    {
      "id": "470f52f8-e68d-412d-bd3a-016f7d94207a",
      "type": "设备",
      "properties": {
        "实体名": "传感器2S5868",
        "设备类型": "传感器",
        "位置": "椅子向后倾斜限位器",
        "操作方式": "探测",
        "操作细节": "支臂处于垂直位置",
        "缩写": null
      }
    },
    {
      "id": "4357891d-3120-4694-94d2-40e9a871de70",
      "type": "设备",
      "properties": {
        "实体名": "传感器2S5874",
        "设备类型": "传感器",
        "位置": "上限位器一盒片叠转移盘",
        "操作方式": "探测",
        "操作细节": "椅子提升活塞在高位置",
        "缩写": null
      }
    },
    {
      "id": "eba30b19-b890-4d74-9bef-7ebbbfd805e1",
      "type": "设备",
      "properties": {
        "实体名": "执行器2Y3137",
        "设备类型": "执行器",
        "位置": "盒片叠椅子",
        "操作方式": "转动指令启动",
        "操作细节": "颠倒椅子提升活塞的指令",
        "缩写": null
      }
    },
    {
      "id": "e8a28f8f-eb86-46c8-8154-e57bffde8a8f",
      "type": "设备",
      "properties": {
        "实体名": "传感器2S5875",
        "设备类型": "传感器",
        "位置": "最低极限位置:盒片叠提升器",
        "操作方式": "检查",
        "操作细节": "椅子位于最低位置",
        "缩写": null
      }
    },
    {
      "id": "b234a16f-4f68-4466-87c3-e61b5b20a6a9",
      "type": "设备",
      "properties": {
        "实体名": "传感器2B526",
        "设备类型": "传感器",
        "位置": "盒片料库",
        "操作方式": "检查",
        "操作细节": "盒片叠检验",
        "缩写": null
      }
    },
    {
      "id": "3149d412-388b-4687-8b7d-703d75623de5",
      "type": "设备",
      "properties": {
        "实体名": "执行器2Y3235",
        "设备类型": "执行器",
        "位置": "盒片叠压紧器",
        "操作方式": "执行器指令控制",
        "操作细节": "置零支臂的前移",
        "缩写": null
      }
    },
    {
      "id": "e685d21e-5af1-4bf2-8022-ff099a5c4b27",
      "type": "设备",
      "properties": {
        "实体名": "电机2M976",
        "设备类型": "电机",
        "位置": "盒片叠供料小车",
        "操作方式": "平移",
        "操作细节": "控制传送器完全后退",
        "缩写": null
      }
    },
    {
      "id": "4e6a407e-51a4-4aed-843a-a020b9867cd3",
      "type": "设备",
      "properties": {
        "实体名": "传感器2S529",
        "设备类型": "传感器",
        "位置": "盒片叠供料载送车后限位器",
        "操作方式": "检查",
        "操作细节": "传送器完全后退的位置",
        "缩写": null
      }
    },
    {
      "id": "359356a5-eb03-4b83-9c47-e67b17b6faa4",
      "type": "二级标题",
      "properties": {
        "实体名": "盒片叠放置到料库中"
      }
    },
    {
      "id": "d7dd7a04-eabf-43c3-930f-6431c246a107",
      "type": "设备",
      "properties": {
        "实体名": "传感器2S5872",
        "设备类型": "传感器",
        "位置": "盒片叠压紧器后移限位器(松开)",
        "操作方式": "检查",
        "操作细节": "置零支臂达到停顿位置",
        "缩写": null
      }
    },
    {
      "id": "d98408af-2ed9-43d5-a757-495fcd0da397",
      "type": "设备",
      "properties": {
        "实体名": "传感器2B524",
        "设备类型": "传感器",
        "位置": "盒片料库的传送臂",
        "操作方式": "检查",
        "操作细节": "盒片低水平位",
        "缩写": null
      }
    },
    {
      "id": "9b9e378a-398e-4e82-a51c-c521d3634841",
      "type": "二级标题",
      "properties": {
        "实体名": "对中内框纸的松卷与同步"
      }
    },
    {
      "id": "0ff53c8d-6938-45cd-9f0e-482b3dc8b493",
      "type": "二级标题",
      "properties": {
        "实体名": "松卷"
      }
    },
    {
      "id": "411881da-27ba-417a-8130-8ac945a6b4da",
      "type": "设备",
      "properties": {
        "实体名": "传感器2B4685",
        "设备类型": "传感器",
        "位置": "内框纸对中检测",
        "操作方式": "探测",
        "操作细节": "标记的读取",
        "缩写": null
      }
    },
    {
      "id": "294b2286-fa37-4bf6-b9c0-dbcc295d0cca",
      "type": "设备",
      "properties": {
        "实体名": "电机2M772",
        "设备类型": "电机",
        "位置": "WRONG ELEMENT",
        "操作方式": "控制",
        "操作细节": "印刷位置的校正",
        "缩写": null
      }
    },
    {
      "id": "32b4446f-9ede-4c1b-83a7-3f0008a6a41b",
      "type": "二级标题",
      "properties": {
        "实体名": "材料同步"
      }
    },
    {
      "id": "073b0627-3f17-466d-a559-e5ceb2f29367",
      "type": "设备",
      "properties": {
        "实体名": "指示灯2H4688",
        "设备类型": "指示灯",
        "位置": "WRONG ELEMENT",
        "操作方式": "发出信号",
        "操作细节": "材料手动对中的必要信号",
        "缩写": null
      }
    },
    {
      "id": "5febe124-b190-4561-8a47-5ba41d2f3d66",
      "type": "设备",
      "properties": {
        "实体名": "传感器2S439",
        "设备类型": "传感器",
        "位置": "内框纸组件上部松卷平台",
        "操作方式": "检查",
        "操作细节": "开启",
        "缩写": null
      }
    },
    {
      "id": "6f853fec-5409-4c9d-9737-dfda08b811fc",
      "type": "设备",
      "properties": {
        "实体名": "传感器2S438",
        "设备类型": "传感器",
        "位置": "内框纸组件下部松卷平台",
        "操作方式": "检查",
        "操作细节": "开启",
        "缩写": null
      }
    },
    {
      "id": "969ff132-f92b-46e8-8658-7db7025fd5bd",
      "type": "设备",
      "properties": {
        "实体名": "旋钮2S146",
        "设备类型": "旋钮",
        "位置": "内框纸组件",
        "操作方式": "脱离",
        "操作细节": "内框纸组件",
        "缩写": null
      }
    },
    {
      "id": "d1fa136a-9ca5-4370-a343-fee10523efab",
      "type": "设备",
      "properties": {
        "实体名": "传感器2B4686",
        "设备类型": "传感器",
        "位置": "内框纸标记检测光电管",
        "操作方式": "探测",
        "操作细节": "到位的标记",
        "缩写": null
      }
    }
  ],
  "relationships": [
    {
      "type": "包含设备",
      "from": "3eb5f2ab-e036-4b7d-91cb-d4fff4a0143b",
      "to": "59b97a49-344f-47d4-8284-680066c6045b"
    },
    {
      "type": "包含设备",
      "from": "3eb5f2ab-e036-4b7d-91cb-d4fff4a0143b",
      "to": "6d943eb5-2048-49e7-9431-71b714735565"
    },
    {
      "type": "包含设备",
      "from": "1f979cc4-6b10-4f92-bdfe-9c4e298b4513",
      "to": "e117c378-1f8c-42fc-aafb-fe9ef290cfb8"
    },
    {
      "type": "包含设备",
      "from": "1f979cc4-6b10-4f92-bdfe-9c4e298b4513",
      "to": "0f333d81-ccbf-4a1b-8296-03b6468700f9"
    },
    {
      "type": "包含设备",
      "from": "1f979cc4-6b10-4f92-bdfe-9c4e298b4513",
      "to": "470f52f8-e68d-412d-bd3a-016f7d94207a"
    },
    {
      "type": "包含设备",
      "from": "1f979cc4-6b10-4f92-bdfe-9c4e298b4513",
      "to": "4357891d-3120-4694-94d2-40e9a871de70"
    },
    {
      "type": "包含设备",
      "from": "1f979cc4-6b10-4f92-bdfe-9c4e298b4513",
      "to": "eba30b19-b890-4d74-9bef-7ebbbfd805e1"
    },
    {
      "type": "包含设备",
      "from": "1f979cc4-6b10-4f92-bdfe-9c4e298b4513",
      "to": "e8a28f8f-eb86-46c8-8154-e57bffde8a8f"
    },
    {
      "type": "包含设备",
      "from": "1f979cc4-6b10-4f92-bdfe-9c4e298b4513",
      "to": "b234a16f-4f68-4466-87c3-e61b5b20a6a9"
    },
    {
      "type": "包含设备",
      "from": "1f979cc4-6b10-4f92-bdfe-9c4e298b4513",
      "to": "3149d412-388b-4687-8b7d-703d75623de5"
    },
    {
      "type": "包含设备",
      "from": "1f979cc4-6b10-4f92-bdfe-9c4e298b4513",
      "to": "e685d21e-5af1-4bf2-8022-ff099a5c4b27"
    },
    {
      "type": "包含设备",
      "from": "1f979cc4-6b10-4f92-bdfe-9c4e298b4513",
      "to": "4e6a407e-51a4-4aed-843a-a020b9867cd3"
    },
    {
      "type": "包含设备",
      "from": "359356a5-eb03-4b83-9c47-e67b17b6faa4",
      "to": "d7dd7a04-eabf-43c3-930f-6431c246a107"
    },
    {
      "type": "包含设备",
      "from": "359356a5-eb03-4b83-9c47-e67b17b6faa4",
      "to": "d98408af-2ed9-43d5-a757-495fcd0da397"
    },
    {
      "type": "包含设备",
      "from": "0ff53c8d-6938-45cd-9f0e-482b3dc8b493",
      "to": "411881da-27ba-417a-8130-8ac945a6b4da"
    },
    {
      "type": "包含设备",
      "from": "0ff53c8d-6938-45cd-9f0e-482b3dc8b493",
      "to": "294b2286-fa37-4bf6-b9c0-dbcc295d0cca"
    },
    {
      "type": "包含设备",
      "from": "32b4446f-9ede-4c1b-83a7-3f0008a6a41b",
      "to": "073b0627-3f17-466d-a559-e5ceb2f29367"
    },
    {
      "type": "包含设备",
      "from": "32b4446f-9ede-4c1b-83a7-3f0008a6a41b",
      "to": "5febe124-b190-4561-8a47-5ba41d2f3d66"
    },
    {
      "type": "包含设备",
      "from": "32b4446f-9ede-4c1b-83a7-3f0008a6a41b",
      "to": "6f853fec-5409-4c9d-9737-dfda08b811fc"
    },
    {
      "type": "包含设备",
      "from": "32b4446f-9ede-4c1b-83a7-3f0008a6a41b",
      "to": "969ff132-f92b-46e8-8658-7db7025fd5bd"
    },
    {
      "type": "包含设备",
      "from": "32b4446f-9ede-4c1b-83a7-3f0008a6a41b",
      "to": "d1fa136a-9ca5-4370-a343-fee10523efab"
    }
  ]
}