{
  "nodes": [
    {
      "id": "c2b2f51a-2f22-4269-99b2-418e66962061",
      "type": "设备",
      "properties": {
        "实体名": "2S147 - 铝箔纸切刀脱离",
        "设备类型": "按钮",
        "位置": "铝箔纸组件脱离检测",
        "操作方式": "旋钮",
        "操作细节": null,
        "缩写": null
      }
    },
    {
      "id": "20e510dd-917f-44dc-90ea-70db6347504f",
      "type": "参见",
      "properties": {
        "实体名": "铝箔纸组件脱离检测 - 铝箔纸组件脱离旋钮,页 2-301"
      }
    },
    {
      "id": "edc9ced7-f1bf-4936-a95e-f35383904dd1",
      "type": "设备",
      "properties": {
        "实体名": "2S1663 - 铝箔纸松卷辊上吸气停止按钮",
        "设备类型": "按钮",
        "位置": "机器端松卷区域铝箔纸的插入按钮",
        "操作方式": null,
        "操作细节": null,
        "缩写": null
      }
    },
    {
      "id": "790c1be7-268e-41e9-8b36-6bc7e9fcd071",
      "type": "参见",
      "properties": {
        "实体名": "铝箔纸松卷辊上吸气停止按钮 - 机器端松卷区域铝箔纸的插入按钮,页 2-281"
      }
    },
    {
      "id": "fc767770-1e81-42c3-95ca-b29782e2a535",
      "type": "设备",
      "properties": {
        "实体名": "2S1664 - 铝箔纸插入按钮 -松卷器区域-",
        "设备类型": "按钮",
        "位置": "机器端松卷区域铝箔纸的插入按钮",
        "操作方式": null,
        "操作细节": null,
        "缩写": null
      }
    },
    {
      "id": "c9e335d3-8427-4e4a-b58c-66aba4708370",
      "type": "图片",
      "properties": {
        "实体名": "图形 5.",
        "图片路径": "images/01955b02-6cff-7e1b-ac84-e8ebec45ae19_24_271_408_1189_930_0.jpg"
      }
    },
    {
      "id": "566372d1-6034-4875-8415-20f21a141825",
      "type": "设备",
      "properties": {
        "实体名": "2S684 - 运行免除旋钮 - PT",
        "设备类型": "旋钮",
        "位置": null,
        "操作方式": null,
        "操作细节": null,
        "缩写": null
      }
    },
    {
      "id": "0d928c3f-bc77-4ce2-8fb6-f4ed149785c7",
      "type": "参见",
      "properties": {
        "实体名": "PT运行免除旋钮, 页 2-55"
      }
    },
    {
      "id": "170fe726-924a-4270-80d5-bc1aa0f46f00",
      "type": "图片",
      "properties": {
        "实体名": "图形 6.",
        "图片路径": "images/01955b02-6cff-7e1b-ac84-e8ebec45ae19_25_102_400_1361_908_0.jpg"
      }
    },
    {
      "id": "8004c617-7723-4239-b4b6-21123d7a42f3",
      "type": "设备",
      "properties": {
        "实体名": "2S683 - X部分运行免除旋钮",
        "设备类型": "旋钮",
        "位置": "X 部分",
        "操作方式": null,
        "操作细节": null,
        "缩写": null
      }
    },
    {
      "id": "1de50920-8fbb-425c-8884-6cb9ee1661b9",
      "type": "参见",
      "properties": {
        "实体名": "运行免除旋钮 - X 部分,页 2-53"
      }
    },
    {
      "id": "03b24281-168e-4a21-bf9b-f1f34b1f90cb",
      "type": "图片",
      "properties": {
        "实体名": "图形 7.",
        "图片路径": "images/01955b02-6cff-7e1b-ac84-e8ebec45ae19_26_181_400_1353_976_0.jpg"
      }
    },
    {
      "id": "97b90cca-751e-42e3-ada7-b2b6f2abb145",
      "type": "设备",
      "properties": {
        "实体名": "S360 - P B 段按钮控制板应急停机按钮",
        "设备类型": "按钮",
        "位置": "PB按钮盘上紧急停机按钮",
        "操作方式": null,
        "操作细节": null,
        "缩写": null
      }
    },
    {
      "id": "f7ca5c7d-d8e1-4c98-98d2-c3d1deda380a",
      "type": "参见",
      "properties": {
        "实体名": "PB按钮盘上紧急停机按钮,页 2-487"
      }
    },
    {
      "id": "9d8ae33d-6968-477d-b986-0d8d5db78c83",
      "type": "设备",
      "properties": {
        "实体名": "2S334 - X出口部分按钮盘上X停机按钮",
        "设备类型": "按钮",
        "位置": "X出口部分按钮盘上的X停机按钮",
        "操作方式": null,
        "操作细节": null,
        "缩写": null
      }
    },
    {
      "id": "47f8c1ce-997f-48f4-b19d-54902a11a1d6",
      "type": "参见",
      "properties": {
        "实体名": "X出口部分按钮盘上的X停机按钮,页 2-485"
      }
    },
    {
      "id": "b7493f5a-02ee-4d04-91ce-297c9c151535",
      "type": "图片",
      "properties": {
        "实体名": "图形 8.",
        "图片路径": "images/01955b02-6cff-7e1b-ac84-e8ebec45ae19_27_101_396_1363_925_0.jpg"
      }
    },
    {
      "id": "17275b58-6741-42bf-bee5-61faa258acd9",
      "type": "设备",
      "properties": {
        "实体名": "S309 - 铝箔纸紧急停机按钮",
        "设备类型": "按钮",
        "位置": "铝箔纸紧急停机按钮",
        "操作方式": null,
        "操作细节": null,
        "缩写": null
      }
    },
    {
      "id": "4f7f5e9e-57d4-41ea-b57b-6662d82c794c",
      "type": "参见",
      "properties": {
        "实体名": "铝箔纸紧急停机按钮,页 2-279"
      }
    },
    {
      "id": "a0236665-cf50-48a9-8ec5-cc63e692ca83",
      "type": "设备",
      "properties": {
        "实体名": "2S318 - 铝箔纸换卷装置的左上芯轴的手动打开按钮",
        "设备类型": "按钮",
        "位置": "铝箔纸换卷左高位与低位芯轴的手动打开按钮",
        "操作方式": null,
        "操作细节": null,
        "缩写": null
      }
    },
    {
      "id": "2d97c421-689d-4ed1-bef1-ed8c4e9109bc",
      "type": "参见",
      "properties": {
        "实体名": "铝箔纸换卷左高位与低位芯轴的手动打开按钮, 页 2-235"
      }
    },
    {
      "id": "5f7078c3-ac16-4467-9456-e3f9a2c46c55",
      "type": "设备",
      "properties": {
        "实体名": "2S319 - 铝箔纸换卷装置的低位芯轴的手动打开按钮",
        "设备类型": "按钮",
        "位置": "铝箔纸换卷左高位与低位芯轴的手动打开按钮",
        "操作方式": null,
        "操作细节": null,
        "缩写": null
      }
    },
    {
      "id": "d2bf48ec-895a-4718-b679-fc45624c4014",
      "type": "设备",
      "properties": {
        "实体名": "2S330 - 铝箔纸换卷置零按钮",
        "设备类型": "按钮",
        "位置": "铝箔纸换卷重新初始化旋钮 - 铝箔纸换卷置零按钮 - 铝箔纸换卷模拟按钮",
        "操作方式": null,
        "操作细节": null,
        "缩写": null
      }
    },
    {
      "id": "ba1aeec9-571a-4699-ad51-c3e90dc36981",
      "type": "参见",
      "properties": {
        "实体名": "铝箔纸换卷重新初始化旋钮 - 铝箔纸换卷置零按钮 - 铝箔纸换卷模拟按钮, 页 2-261"
      }
    },
    {
      "id": "e0d6990d-a964-46b0-a50e-1d6bc6b678f9",
      "type": "设备",
      "properties": {
        "实体名": "2S331 - 铝箔纸换卷模拟按钮",
        "设备类型": "按钮",
        "位置": "铝箔纸换卷重新初始化旋钮 - 铝箔纸换卷置零按钮 - 铝箔纸换卷模拟按钮",
        "操作方式": null,
        "操作细节": null,
        "缩写": null
      }
    },
    {
      "id": "94654847-d3b8-41ee-9baf-410cf52d59c4",
      "type": "图片",
      "properties": {
        "实体名": "图形 9.",
        "图片路径": "images/01955b02-6cff-7e1b-ac84-e8ebec45ae19_28_213_410_1296_778_0.jpg"
      }
    }
  ],
  "relationships": [
    {
      "type": "有参见",
      "from": "c2b2f51a-2f22-4269-99b2-418e66962061",
      "to": "20e510dd-917f-44dc-90ea-70db6347504f"
    },
    {
      "type": "有参见",
      "from": "edc9ced7-f1bf-4936-a95e-f35383904dd1",
      "to": "790c1be7-268e-41e9-8b36-6bc7e9fcd071"
    },
    {
      "type": "有参见",
      "from": "fc767770-1e81-42c3-95ca-b29782e2a535",
      "to": "790c1be7-268e-41e9-8b36-6bc7e9fcd071"
    },
    {
      "type": "有图片",
      "from": "c2b2f51a-2f22-4269-99b2-418e66962061",
      "to": "c9e335d3-8427-4e4a-b58c-66aba4708370"
    },
    {
      "type": "有参见",
      "from": "566372d1-6034-4875-8415-20f21a141825",
      "to": "0d928c3f-bc77-4ce2-8fb6-f4ed149785c7"
    },
    {
      "type": "有图片",
      "from": "566372d1-6034-4875-8415-20f21a141825",
      "to": "170fe726-924a-4270-80d5-bc1aa0f46f00"
    },
    {
      "type": "有参见",
      "from": "8004c617-7723-4239-b4b6-21123d7a42f3",
      "to": "1de50920-8fbb-425c-8884-6cb9ee1661b9"
    },
    {
      "type": "有图片",
      "from": "8004c617-7723-4239-b4b6-21123d7a42f3",
      "to": "03b24281-168e-4a21-bf9b-f1f34b1f90cb"
    },
    {
      "type": "有参见",
      "from": "97b90cca-751e-42e3-ada7-b2b6f2abb145",
      "to": "f7ca5c7d-d8e1-4c98-98d2-c3d1deda380a"
    },
    {
      "type": "有参见",
      "from": "9d8ae33d-6968-477d-b986-0d8d5db78c83",
      "to": "47f8c1ce-997f-48f4-b19d-54902a11a1d6"
    },
    {
      "type": "有图片",
      "from": "97b90cca-751e-42e3-ada7-b2b6f2abb145",
      "to": "b7493f5a-02ee-4d04-91ce-297c9c151535"
    },
    {
      "type": "有参见",
      "from": "17275b58-6741-42bf-bee5-61faa258acd9",
      "to": "4f7f5e9e-57d4-41ea-b57b-6662d82c794c"
    },
    {
      "type": "有参见",
      "from": "a0236665-cf50-48a9-8ec5-cc63e692ca83",
      "to": "2d97c421-689d-4ed1-bef1-ed8c4e9109bc"
    },
    {
      "type": "有参见",
      "from": "5f7078c3-ac16-4467-9456-e3f9a2c46c55",
      "to": "2d97c421-689d-4ed1-bef1-ed8c4e9109bc"
    },
    {
      "type": "有参见",
      "from": "d2bf48ec-895a-4718-b679-fc45624c4014",
      "to": "ba1aeec9-571a-4699-ad51-c3e90dc36981"
    },
    {
      "type": "有参见",
      "from": "e0d6990d-a964-46b0-a50e-1d6bc6b678f9",
      "to": "ba1aeec9-571a-4699-ad51-c3e90dc36981"
    },
    {
      "type": "有图片",
      "from": "17275b58-6741-42bf-bee5-61faa258acd9",
      "to": "94654847-d3b8-41ee-9baf-410cf52d59c4"
    }
  ]
}