{
  "nodes": [
    {
      "id": "7d629c45-b610-4228-b8b7-2abcc738da05",
      "type": "三级标题",
      "properties": {
        "实体名": "( X ) 左下护罩"
      }
    },
    {
      "id": "ec790a3d-e650-4454-af0e-36985795347f",
      "type": "设备",
      "properties": {
        "实体名": "2S4015 - X 左下护门",
        "缩写": "2S4015",
        "功能": "传感器 2S4015探测左下活动护罩打开"
      }
    },
    {
      "id": "4ab8b072-c65b-4c54-9d6e-6a4555366576",
      "type": "检测异常",
      "properties": {
        "实体名": "活动护罩打开时"
      }
    },
    {
      "id": "aef90d74-bcae-48d5-b19b-188d2ff464c3",
      "type": "异常动作",
      "properties": {
        "实体名": "停止机器"
      }
    },
    {
      "id": "d9577f51-df84-49da-9465-9ae1b2c606f3",
      "type": "异常动作",
      "properties": {
        "实体名": "发出typology ABNORMAL 左下安全护门报警信号"
      }
    },
    {
      "id": "97adda32-c3e4-496f-b075-6e673c9ee583",
      "type": "检测异常",
      "properties": {
        "实体名": "若在预定时间内没有探测出锁定"
      }
    },
    {
      "id": "2accdd36-8848-49b8-af61-9b45202832dc",
      "type": "异常动作",
      "properties": {
        "实体名": "发出报警信息typology EMERGENCY 护罩故障"
      }
    },
    {
      "id": "6f1dff9a-5a95-4e49-b849-67039f97a228",
      "type": "检测异常",
      "properties": {
        "实体名": "当机器从停止状态变为恢复或运行状态时,若没有锁定"
      }
    },
    {
      "id": "401929fc-a15b-483a-953a-49a211b43610",
      "type": "图片",
      "properties": {
        "实体名": "图形 55 . X 气动护罩安全带",
        "图片路径": "images/01955b02-6cff-7e1b-ac84-e8ebec45ae19_110_335_958_1055_793_0.jpg"
      }
    },
    {
      "id": "4c0078a0-bf97-4f97-b388-8658bcb8f43a",
      "type": "设备",
      "properties": {
        "实体名": "2S4029 - X气动护罩安全带",
        "缩写": "2S4029"
      }
    },
    {
      "id": "835bc09f-25af-4f54-9d01-73d5d08246c5",
      "type": "设备",
      "properties": {
        "实体名": "2S4030 - X气动护罩安全带",
        "缩写": "2S4030"
      }
    },
    {
      "id": "e1f20c48-b821-4e6f-a87f-29aef8b920a3",
      "type": "设备",
      "properties": {
        "实体名": "2S4031 - X气动护罩安全带",
        "缩写": "2S4031"
      }
    },
    {
      "id": "f2f8c8e4-e16b-421b-bbda-2f3cba9769e5",
      "type": "设备",
      "properties": {
        "实体名": "2S4032 - X气动护罩安全带",
        "缩写": "2S4032"
      }
    },
    {
      "id": "b8c3490d-3602-416b-9c85-079a5345be3a",
      "type": "设备",
      "properties": {
        "实体名": "2S4033 - X气动护罩安全带",
        "缩写": "2S4033"
      }
    },
    {
      "id": "66f8ddd8-184a-405b-a456-a8cdd481c1d9",
      "type": "设备",
      "properties": {
        "实体名": "2S4034 - X气动护罩安全带",
        "缩写": "2S4034"
      }
    },
    {
      "id": "7eb3a2ca-279c-424d-98fe-6ec64886c25e",
      "type": "设备",
      "properties": {
        "实体名": "2S4035 - X气动护罩安全带",
        "缩写": "2S4035"
      }
    },
    {
      "id": "746eb641-e743-4b01-9f46-fb59cbf26369",
      "type": "设备",
      "properties": {
        "实体名": "2S4045 - X气动护罩安全带",
        "缩写": "2S4045"
      }
    },
    {
      "id": "452472a3-9d2c-41f1-b492-1948bcf5b904",
      "type": "功能",
      "properties": {
        "实体名": "用于操作员的安全保护",
        "功能类型": "安全保护"
      }
    },
    {
      "id": "3dd2f5ca-db4e-479f-bf54-2bfb742e2f7a",
      "type": "检测异常",
      "properties": {
        "实体名": "若在活动护罩下降过程中,安全带探测出阻塞"
      }
    },
    {
      "id": "a58c5e0b-0f89-406f-bc44-cc41577efe08",
      "type": "异常动作",
      "properties": {
        "实体名": "中断下降,并自动控制上升"
      }
    },
    {
      "id": "ae1cc27f-276f-445b-9c8a-5af31eda07d2",
      "type": "异常动作",
      "properties": {
        "实体名": "发出typology EMERGENCY 中上护门安全杆的报警信号"
      }
    },
    {
      "id": "9472767e-06ce-4f45-a33c-78636274b365",
      "type": "图片",
      "properties": {
        "实体名": "图形 56.",
        "图片路径": "images/01955b02-6cff-7e1b-ac84-e8ebec45ae19_112_517_1267_628_731_0.jpg"
      }
    },
    {
      "id": "1d7d0016-a1ac-484a-81fc-a087fecfabe3",
      "type": "三级标题",
      "properties": {
        "实体名": "CARTER X 空压机的原理及功能"
      }
    },
    {
      "id": "117f20ed-230e-4015-a25e-d2b76a19646a",
      "type": "设备",
      "properties": {
        "实体名": "2S1280 - X护罩气动装置的气压检测",
        "缩写": "2S1280",
        "功能": "感应器2S1280用于检查安全执行器2Y1001的运行状况"
      }
    },
    {
      "id": "34d69379-6ac5-4f95-85ba-94ca4d425676",
      "type": "检测异常",
      "properties": {
        "实体名": "若在执行器2Y1001转换之后,在气动环路内没有出现压力变化"
      }
    },
    {
      "id": "1755c1c4-f7fa-4c4a-90fd-e8f9b5a5da35",
      "type": "异常动作",
      "properties": {
        "实体名": "停止机器"
      }
    },
    {
      "id": "b2d4b83e-081a-47fb-8967-aa90166dc436",
      "type": "异常动作",
      "properties": {
        "实体名": "发出报警信息typology ABNORMAL 中上部护罩安全 E.V.故障"
      }
    },
    {
      "id": "eac207a8-246d-4832-a9f1-14fd784318af",
      "type": "三级标题",
      "properties": {
        "实体名": "校准:压力计 SUNX DP2-42E"
      }
    },
    {
      "id": "47b89c4a-3fac-445f-b267-ef3de13cf3c4",
      "type": "校准部件",
      "properties": {
        "实体名": "压力计 SUNX DP2-42E"
      }
    },
    {
      "id": "a5d4a940-fcec-45a0-bd29-7af18a2f510a",
      "type": "校准操作",
      "properties": {
        "实体名": "保护装置的解锁",
        "操作描述": "按下大约4秒钟按钮MODE,直至在显示器上出现字样 “OFF”"
      }
    },
    {
      "id": "3c56ea9f-d8cb-4dec-bc8b-b2fffd383816",
      "type": "校准操作",
      "properties": {
        "实体名": "零点的调节",
        "操作描述": "关闭压缩空气,并断开传感器上的管子。同时按下按钮UP和DOWN,在显示器上的读数将变为零"
      }
    },
    {
      "id": "dad74de2-105e-4873-902d-ec37903f802b",
      "type": "校准操作",
      "properties": {
        "实体名": "测量单位的设定",
        "操作描述": "同时按下按钮UP和MODE,在 1 秒钟后将在显示器 3 上出现闪烁字符。用按钮UP来选择字符,用按钮DOWN来改变选择的字符数值,用按钮MODE来确认所作的选择"
      }
    },
    {
      "id": "c16f186f-0a87-4881-8824-06d43a39afde",
      "type": "校准操作",
      "properties": {
        "实体名": "工作临界值的设定",
        "操作描述": "按下一次按钮MODE,在显示器上将出现字样P1:用按钮UP和DOWN来设定数值,低于该数值时机器将会由于气压不足而停机 (不得低于4巴)"
      }
    },
    {
      "id": "ffbb1e47-893c-47f7-a3ab-6b707389bd4d",
      "type": "校准操作",
      "properties": {
        "实体名": "设定的参数保护",
        "操作描述": "为了保护设定的数值,可按下大约4秒钟按钮MODE,直至在显示器上出现字样“ON”"
      }
    }
  ],
  "relationships": [
    {
      "type": "包含设备",
      "from": "7d629c45-b610-4228-b8b7-2abcc738da05",
      "to": "ec790a3d-e650-4454-af0e-36985795347f"
    },
    {
      "type": "有功能",
      "from": "ec790a3d-e650-4454-af0e-36985795347f",
      "to": "452472a3-9d2c-41f1-b492-1948bcf5b904"
    },
    {
      "type": "有检测异常",
      "from": "ec790a3d-e650-4454-af0e-36985795347f",
      "to": "4ab8b072-c65b-4c54-9d6e-6a4555366576"
    },
    {
      "type": "导致异常动作",
      "from": "4ab8b072-c65b-4c54-9d6e-6a4555366576",
      "to": "aef90d74-bcae-48d5-b19b-188d2ff464c3"
    },
    {
      "type": "导致异常动作",
      "from": "4ab8b072-c65b-4c54-9d6e-6a4555366576",
      "to": "d9577f51-df84-49da-9465-9ae1b2c606f3"
    },
    {
      "type": "有检测异常",
      "from": "ec790a3d-e650-4454-af0e-36985795347f",
      "to": "97adda32-c3e4-496f-b075-6e673c9ee583"
    },
    {
      "type": "导致异常动作",
      "from": "97adda32-c3e4-496f-b075-6e673c9ee583",
      "to": "2accdd36-8848-49b8-af61-9b45202832dc"
    },
    {
      "type": "有检测异常",
      "from": "ec790a3d-e650-4454-af0e-36985795347f",
      "to": "6f1dff9a-5a95-4e49-b849-67039f97a228"
    },
    {
      "type": "导致异常动作",
      "from": "6f1dff9a-5a95-4e49-b849-67039f97a228",
      "to": "2accdd36-8848-49b8-af61-9b45202832dc"
    },
    {
      "type": "有图片",
      "from": "7d629c45-b610-4228-b8b7-2abcc738da05",
      "to": "401929fc-a15b-483a-953a-49a211b43610"
    },
    {
      "type": "包含设备",
      "from": "7d629c45-b610-4228-b8b7-2abcc738da05",
      "to": "4c0078a0-bf97-4f97-b388-8658bcb8f43a"
    },
    {
      "type": "包含设备",
      "from": "7d629c45-b610-4228-b8b7-2abcc738da05",
      "to": "835bc09f-25af-4f54-9d01-73d5d08246c5"
    },
    {
      "type": "包含设备",
      "from": "7d629c45-b610-4228-b8b7-2abcc738da05",
      "to": "e1f20c48-b821-4e6f-a87f-29aef8b920a3"
    },
    {
      "type": "包含设备",
      "from": "7d629c45-b610-4228-b8b7-2abcc738da05",
      "to": "f2f8c8e4-e16b-421b-bbda-2f3cba9769e5"
    },
    {
      "type": "包含设备",
      "from": "7d629c45-b610-4228-b8b7-2abcc738da05",
      "to": "b8c3490d-3602-416b-9c85-079a5345be3a"
    },
    {
      "type": "包含设备",
      "from": "7d629c45-b610-4228-b8b7-2abcc738da05",
      "to": "66f8ddd8-184a-405b-a456-a8cdd481c1d9"
    },
    {
      "type": "包含设备",
      "from": "7d629c45-b610-4228-b8b7-2abcc738da05",
      "to": "7eb3a2ca-279c-424d-98fe-6ec64886c25e"
    },
    {
      "type": "包含设备",
      "from": "7d629c45-b610-4228-b8b7-2abcc738da05",
      "to": "746eb641-e743-4b01-9f46-fb59cbf26369"
    },
    {
      "type": "有功能",
      "from": "4c0078a0-bf97-4f97-b388-8658bcb8f43a",
      "to": "452472a3-9d2c-41f1-b492-1948bcf5b904"
    },
    {
      "type": "有检测异常",
      "from": "4c0078a0-bf97-4f97-b388-8658bcb8f43a",
      "to": "3dd2f5ca-db4e-479f-bf54-2bfb742e2f7a"
    },
    {
      "type": "导致异常动作",
      "from": "3dd2f5ca-db4e-479f-bf54-2bfb742e2f7a",
      "to": "a58c5e0b-0f89-406f-bc44-cc41577efe08"
    },
    {
      "type": "导致异常动作",
      "from": "3dd2f5ca-db4e-479f-bf54-2bfb742e2f7a",
      "to": "ae1cc27f-276f-445b-9c8a-5af31eda07d2"
    },
    {
      "type": "有图片",
      "from": "7d629c45-b610-4228-b8b7-2abcc738da05",
      "to": "9472767e-06ce-4f45-a33c-78636274b365"
    },
    {
      "type": "包含设备",
      "from": "1d7d0016-a1ac-484a-81fc-a087fecfabe3",
      "to": "117f20ed-230e-4015-a25e-d2b76a19646a"
    },
    {
      "type": "有检测异常",
      "from": "117f20ed-230e-4015-a25e-d2b76a19646a",
      "to": "34d69379-6ac5-4f95-85ba-94ca4d425676"
    },
    {
      "type": "导致异常动作",
      "from": "34d69379-6ac5-4f95-85ba-94ca4d425676",
      "to": "1755c1c4-f7fa-4c4a-90fd-e8f9b5a5da35"
    },
    {
      "type": "导致异常动作",
      "from": "34d69379-6ac5-4f95-85ba-94ca4d425676",
      "to": "b2d4b83e-081a-47fb-8967-aa90166dc436"
    },
    {
      "type": "有校准部件",
      "from": "eac207a8-246d-4832-a9f1-14fd784318af",
      "to": "47b89c4a-3fac-445f-b267-ef3de13cf3c4"
    },
    {
      "type": "有校准操作",
      "from": "47b89c4a-3fac-445f-b267-ef3de13cf3c4",
      "to": "a5d4a940-fcec-45a0-bd29-7af18a2f510a"
    },
    {
      "type": "有校准操作",
      "from": "47b89c4a-3fac-445f-b267-ef3de13cf3c4",
      "to": "3c56ea9f-d8cb-4dec-bc8b-b2fffd383816"
    },
    {
      "type": "有校准操作",
      "from": "47b89c4a-3fac-445f-b267-ef3de13cf3c4",
      "to": "dad74de2-105e-4873-902d-ec37903f802b"
    },
    {
      "type": "有校准操作",
      "from": "47b89c4a-3fac-445f-b267-ef3de13cf3c4",
      "to": "c16f186f-0a87-4881-8824-06d43a39afde"
    },
    {
      "type": "有校准操作",
      "from": "47b89c4a-3fac-445f-b267-ef3de13cf3c4",
      "to": "ffbb1e47-893c-47f7-a3ab-6b707389bd4d"
    }
  ]
}